Metadata-Version: 2.1
Name: otf-addons-vault
Version: 24.18.0
Summary: Addons for opentaskpy, giving it the ability to read variables from Hashicorp Vault
Author-email: Adam McDonagh <adam@elitemonkey.net>
License: GPLv3
Project-URL: Homepage, https://github.com/adammcdonagh/otf-addons-vault
Project-URL: Bug Tracker, https://github.com/adammcdonagh/otf-addons-vault/issues
Project-URL: Changelog, https://github.com/adammcdonagh/otf-addons-vault/blob/main/CHANGELOG.md
Keywords: automation,task,framework,hashicorp,vault,secrets,otf
Classifier: Programming Language :: Python :: 3
Classifier: License :: OSI Approved :: GNU General Public License v3 (GPLv3)
Classifier: Operating System :: POSIX
Requires-Python: >=3.11
License-File: LICENSE
License-File: AUTHORS
Requires-Dist: boto3>=1.26
Requires-Dist: opentaskpy>=v24.13.1
Provides-Extra: dev
Requires-Dist: pytest-shell; extra == "dev"
Requires-Dist: types-requests; extra == "dev"
Requires-Dist: types-python-dateutil; extra == "dev"
Requires-Dist: black>=24.1.1; extra == "dev"
Requires-Dist: isort; extra == "dev"
Requires-Dist: pytest; extra == "dev"
Requires-Dist: bumpver; extra == "dev"
Requires-Dist: pytest-shell; extra == "dev"
Requires-Dist: lovely-pytest-docker; extra == "dev"
Requires-Dist: pre-commit; extra == "dev"
Requires-Dist: pylint; extra == "dev"
Requires-Dist: pydantic; extra == "dev"
Requires-Dist: mypy; extra == "dev"
Requires-Dist: ruff; extra == "dev"
Requires-Dist: coverage; extra == "dev"
Requires-Dist: pytest-cov; extra == "dev"
Requires-Dist: hvac; extra == "dev"
